[
  {
    "title": "9am Call Bank",
    "text": "Check payments",
    "id": "test"
  },
  {
    "title": "Meeting with staff",
    "text": "Discuss shift changes",
    "id": "7709"
  },
  {
    "title": "Finalise Roster",
    "text": "Check if Jenna can work Fridays",
    "id": "1677"
  },
  {
    "title": "Tuesday Finish Payroll",
    "text": "Ring accountant",
    "id": "535a"
  },
  {
    "title": "Organise monthly clean",
    "text": "Check availability of new company",
    "id": "4d74"
  }
]
